pytest_resttest/__init__.py
pytest_resttest/__main__.py
pytest_resttest/compare/__init__.py
pytest_resttest/compare/complex_compare.py
pytest_resttest/compare/partial.py
pytest_resttest/compare/repr.py
pytest_resttest/jinja/__init__.py
pytest_resttest/jinja/env.py
pytest_resttest/jinja/evaluate.py
pytest_resttest/jinja/filters.py
pytest_resttest/jinja/globals.py
pytest_resttest/jinja/tests.py
pytest_resttest/lib/__init__.py
pytest_resttest/lib/format_struct.py
pytest_resttest/lib/indent.py
pytest_resttest/lib/stored_result.py
pytest_resttest/lib/yaml.py
pytest_resttest/models/__init__.py
pytest_resttest/models/base.py
pytest_resttest/models/exceptions.py
pytest_resttest/models/fixture.py
pytest_resttest/models/fixtures/__init__.py
pytest_resttest/models/fixtures/clean_db.py
pytest_resttest/models/fixtures/evaluate.py
pytest_resttest/models/http_types.py
pytest_resttest/models/jinja.py
pytest_resttest/models/suite.py
pytest_resttest/models/test_types/__init__.py
pytest_resttest/models/test_types/base.py
pytest_resttest/models/test_types/db.py
pytest_resttest/models/test_types/evaluate.py
pytest_resttest/models/test_types/http.py
pytest_resttest/models/test_types/sleep.py
pytest_resttest/pytest_hooks.py
pytest_resttest/reporter/__init__.py
pytest_resttest/reporter/base.py
pytest_resttest/reporter/console.py
pytest_resttest/runner.py
pytest_resttest-1.0.2.dist-info/METADATA
pytest_resttest-1.0.2.dist-info/WHEEL
pytest_resttest-1.0.2.dist-info/entry_points.txt
pytest_resttest-1.0.2.dist-info/licenses/LICENSE
pytest_resttest-1.0.2.dist-info/RECORD
