Metadata-Version: 2.4
Name: pytest-resttest
Version: 1.0.2
Summary: A REST API testing framework for Python, as plugin for pytest. Uses simple and readable YAML files for specifying test cases.
License-Expression: MIT
License-File: LICENSE
Author: Michal Kuchta
Author-email: niximor@gmail.com
Requires-Python: >=3.13,<4.0.0
Classifier: Programming Language :: Python :: 3
Classifier: Development Status :: 5 - Production/Stable
Classifier: Intended Audience :: Developers
Classifier: Topic :: Software Development :: Testing
Classifier: License :: OSI Approved :: MIT License
Classifier: Operating System :: OS Independent
Requires-Dist: asgi-lifespan (>=2.1.0,<3.0.0)
Requires-Dist: assertpy (>=1.1,<2.0)
Requires-Dist: gcm-asyncdb (>=2.3.0,<3.0.0)
Requires-Dist: httpx (>=0.28.1,<0.29.0)
Requires-Dist: isodate (>=0.7.2,<0.8.0)
Requires-Dist: jinja2 (>=3.1.6,<4.0.0)
Requires-Dist: orjson (>=3.11.5,<4.0.0)
Requires-Dist: pydantic (>=2.11.7,<3.0.0)
Requires-Dist: ruamel-yaml (>=0.18.14,<0.19.0)
Requires-Dist: termcolor (>=3.1.0,<4.0.0)
Project-URL: Homepage, https://gitlab.com/gcm-cz/pytest-resttest
Project-URL: Issues, https://gitlab.com/gcm-cz/pytest-resttest/-/issues
Project-URL: Repository, https://gitlab.com/gcm-cz/pytest-resttest
